MANIFEST.in
setup.py
musicsync/__init__.py
musicsync/auth.py
musicsync/config.py
musicsync/copy.py
musicsync/exceptions.py
musicsync/gpm.py
musicsync/musicclient.py
musicsync/serializers.py
musicsync/spotify.py
musicsync/utils.py
musicsync.egg-info/PKG-INFO
musicsync.egg-info/SOURCES.txt
musicsync.egg-info/dependency_links.txt
musicsync.egg-info/not-zip-safe
musicsync.egg-info/requires.txt
musicsync.egg-info/top_level.txt