Metadata-Version: 1.0
Name: musicsync
Version: 0.3.2
Summary: Sync songs between music streaming services
Home-page: https://github.com/moxuz/musicsync
Author: Chris Pouliot
Author-email: me@chrispouliot.codes
License: MIT
Platform: UNKNOWN
